inflection.py
inflection-0.4.0.dist-info/LICENSE
inflection-0.4.0.dist-info/METADATA
inflection-0.4.0.dist-info/WHEEL
inflection-0.4.0.dist-info/top_level.txt
inflection-0.4.0.dist-info/RECORD
